mopidy_pibox/__init__.py
mopidy_pibox/api.py
mopidy_pibox/ext.conf
mopidy_pibox/frontend.py
mopidy_pibox/pibox.py
mopidy_pibox/routing.py
mopidy_pibox/socket.py
mopidy_pibox/static/index.html
mopidy_pibox/static/manifest.json
mopidy_pibox/static/assets/DisplayPage-CDWcXc8N.js
mopidy_pibox/static/assets/NewSessionPage-CcpJIUK4.js
mopidy_pibox/static/assets/SessionPage-CNVQx88E.js
mopidy_pibox/static/assets/index-B-ALXia5.css
mopidy_pibox/static/assets/index-eJVyzfdY.js
mopidy_pibox/static/assets/logo-Dc05Dibe.png
mopidy_pibox/static/assets/logo-black-DSbqoc37.png
mopidy_pibox/static/assets/placeholder-WWDZBqe9.png
mopidy_pibox-3.0.5.dist-info/licenses/LICENSE
mopidy_pibox-3.0.5.dist-info/METADATA
mopidy_pibox-3.0.5.dist-info/WHEEL
mopidy_pibox-3.0.5.dist-info/entry_points.txt
mopidy_pibox-3.0.5.dist-info/top_level.txt
mopidy_pibox-3.0.5.dist-info/RECORD
