Metadata-Version: 2.4
Name: Mopidy-Pibox
Version: 3.0.5
Summary: Mopidy extension for jukebox client
Home-page: https://github.com/gbannerman/mopidy-pibox
Author: Gavin Bannerman
Author-email: pibox@gavinb.site
License: Apache License, Version 2.0
Classifier: Environment :: No Input/Output (Daemon)
Classifier: Intended Audience :: End Users/Desktop
Classifier: License :: OSI Approved :: Apache Software License
Classifier: Operating System :: OS Independent
Classifier: Programming Language :: Python :: 3
Classifier: Programming Language :: Python :: 3.9
Classifier: Programming Language :: Python :: 3.10
Classifier: Programming Language :: Python :: 3.11
Classifier: Programming Language :: Python :: 3.12
Classifier: Topic :: Multimedia :: Sound/Audio :: Players
Requires-Python: >=3.9
License-File: LICENSE
Requires-Dist: Mopidy>=3.0.0
Requires-Dist: Pykka>=2.0.1
Requires-Dist: PyGObject==3.50
Requires-Dist: setuptools
Provides-Extra: lint
Requires-Dist: ruff==0.4.5; extra == "lint"
Requires-Dist: check-manifest; extra == "lint"
Provides-Extra: test
Requires-Dist: pytest==8.2.1; extra == "test"
Requires-Dist: pytest-cov==5.0.0; extra == "test"
Provides-Extra: dev
Requires-Dist: ruff==0.4.5; extra == "dev"
Requires-Dist: check-manifest; extra == "dev"
Requires-Dist: pytest==8.2.1; extra == "dev"
Requires-Dist: pytest-cov==5.0.0; extra == "dev"
Requires-Dist: tox; extra == "dev"
Dynamic: license-file
